LICENSE
MANIFEST.in
README.md
setup.py
tap_trello/__init__.py
tap_trello/client.py
tap_trello/discover.py
tap_trello/streams.py
tap_trello/sync.py
tap_trello.egg-info/PKG-INFO
tap_trello.egg-info/SOURCES.txt
tap_trello.egg-info/dependency_links.txt
tap_trello.egg-info/entry_points.txt
tap_trello.egg-info/requires.txt
tap_trello.egg-info/top_level.txt
tap_trello/schemas/actions.json
tap_trello/schemas/boards.json
tap_trello/schemas/cards.json
tap_trello/schemas/checklists.json
tap_trello/schemas/lists.json
tap_trello/schemas/users.json