Metadata-Version: 2.1
Name: tap-trello
Version: 0.1.0
Summary: Singer.io tap for extracting data from Trello API
Home-page: http://singer.io
Author: Stitch
License: UNKNOWN
Platform: UNKNOWN
Classifier: Programming Language :: Python :: 3 :: Only
Provides-Extra: dev
